doc_switch/__init__.py
doc_switch/cli.py
doc_switch/doc_switch.py
doc_switch-0.1.1.dist-info/AUTHORS.md
doc_switch-0.1.1.dist-info/LICENSE
doc_switch-0.1.1.dist-info/METADATA
doc_switch-0.1.1.dist-info/WHEEL
doc_switch-0.1.1.dist-info/entry_points.txt
doc_switch-0.1.1.dist-info/top_level.txt
doc_switch-0.1.1.dist-info/RECORD
