Metadata-Version: 2.1
Name: doc-switch
Version: 0.1.1
Summary: DocSwitch gives you the freedom to write your Python documentation in any format you want, switching between them effortlessly.
Home-page: https://github.com/cutewarriorlover/doc_switch
Author: Cutewarriorlover
Author-email: cutewarriorlover@gmail.com
License: MIT license
Keywords: doc_switch
Platform: UNKNOWN
Classifier: Development Status :: 2 - Pre-Alpha
Classifier: Intended Audience :: Developers
Classifier: License :: OSI Approved :: MIT License
Classifier: Natural Language :: English
Classifier: Programming Language :: Python :: 3
Classifier: Programming Language :: Python :: 3.6
Classifier: Programming Language :: Python :: 3.7
Classifier: Programming Language :: Python :: 3.8
Classifier: Programming Language :: Python :: Implementation :: CPython
Requires-Python: >=3.6
Requires-Dist: Click (>=7.0)
